pelican_embed_microblog/__init__.py
pelican_embed_microblog/_version.py
pelican_embed_microblog/embed_microblog.py
pelican_embed_microblog-1.1.0.dist-info/METADATA
pelican_embed_microblog-1.1.0.dist-info/WHEEL
pelican_embed_microblog-1.1.0.dist-info/licenses/LICENSE
pelican_embed_microblog-1.1.0.dist-info/RECORD
