Metadata-Version: 2.1
Name: pelican-embed-microblog
Version: 1.1.0
Summary: A Pelican plugin that wrapps references to twitter et al. Forked from pelican-advance-embed-tweet
Author: Fundor333, Sven Kreiss
Author-email: Chris Rose <offline@offby1.net>
License: MIT License
License-File: LICENSE
Keywords: blog,pelican,social networking,static site generator
Requires-Python: >=3.9
Requires-Dist: beautifulsoup4<5.0,>=4.11
Provides-Extra: dev
Requires-Dist: black; extra == 'dev'
Requires-Dist: doc2dash; extra == 'dev'
Requires-Dist: flake8; extra == 'dev'
Requires-Dist: pelican-embed-microblog[docs,tests]; extra == 'dev'
Requires-Dist: pytest-mypy; extra == 'dev'
Requires-Dist: towncrier; extra == 'dev'
Requires-Dist: twine; extra == 'dev'
Provides-Extra: docs
Requires-Dist: alabaster~=0.7; extra == 'docs'
Requires-Dist: sphinx~=4.0; extra == 'docs'
Provides-Extra: tests
Requires-Dist: coverage[toml]; extra == 'tests'
Requires-Dist: pelican; extra == 'tests'
Requires-Dist: pytest-cov; extra == 'tests'
Requires-Dist: pytest-sugar; extra == 'tests'
Requires-Dist: pytest-xdist; extra == 'tests'
Requires-Dist: pytest>=5.0; extra == 'tests'
